{
   "LB10" : {
      "xFrom" : 50,
      "xTo" : 805,
      "yFrom" : 26,
      "yTo" : 116
   },
   "LB100" : {
      "xFrom" : 565,
      "xTo" : 870,
      "yFrom" : 26,
      "yTo" : 116
   },
   "LB101" : {
      "xFrom" : 555,
      "xTo" : 30,
      "yFrom" : 26,
      "yTo" : 146
   },
   "LB102" : {
      "xFrom" : 505,
      "xTo" : 475,
      "yFrom" : 26,
      "yTo" : 86
   },
   "LB103" : {
      "xFrom" : 515,
      "xTo" : 800,
      "yFrom" : 26,
      "yTo" : 56
   },
   "LB104" : {
      "xFrom" : 520,
      "xTo" : 805,
      "yFrom" : 26,
      "yTo" : 56
   },
   "LB105" : {
      "xFrom" : 550,
      "xTo" : 810,
      "yFrom" : 26,
      "yTo" : 56
   },
   "LB106" : {
      "xFrom" : 715,
      "xTo" : 540,
      "yFrom" : 26,
      "yTo" : 146
   },
   "LB107" : {
      "xFrom" : 580,
      "xTo" : 530,
      "yFrom" : 26,
      "yTo" : 146
   },
   "LB108" : {
      "xFrom" : 770,
      "xTo" : 55,
      "yFrom" : 26,
      "yTo" : 86
   },
   "LB109" : {
      "xFrom" : 595,
      "xTo" : 480,
      "yFrom" : 26,
      "yTo" : 86
   },
   "LB11" : {
      "xFrom" : 265,
      "xTo" : 460,
      "yFrom" : 26,
      "yTo" : 146
   },
   "LB110" : {
      "xFrom" : 740,
      "xTo" : 545,
      "yFrom" : 26,
      "yTo" : 146
   },
   "LB111" : {
      "xFrom" : 640,
      "xTo" : 490,
      "yFrom" : 26,
      "yTo" : 86
   },
   "LB112" : {
      "xFrom" : 695,
      "xTo" : 45,
      "yFrom" : 26,
      "yTo" : 86
   },
   "LB113" : {
      "xFrom" : 710,
      "xTo" : 65,
      "yFrom" : 26,
      "yTo" : 116
   },
   "LB114" : {
      "xFrom" : 630,
      "xTo" : 30,
      "yFrom" : 26,
      "yTo" : 86
   },
   "LB115" : {
      "xFrom" : 750,
      "xTo" : 470,
      "yFrom" : 26,
      "yTo" : 116
   },
   "LB116" : {
      "xFrom" : 675,
      "xTo" : 885,
      "yFrom" : 26,
      "yTo" : 116
   },
   "LB117" : {
      "xFrom" : 700,
      "xTo" : 10,
      "yFrom" : 26,
      "yTo" : 56
   },
   "LB118" : {
      "xFrom" : 605,
      "xTo" : 875,
      "yFrom" : 26,
      "yTo" : 116
   },
   "LB119" : {
      "xFrom" : 665,
      "xTo" : 850,
      "yFrom" : 26,
      "yTo" : 146
   },
   "LB12" : {
      "xFrom" : 85,
      "xTo" : 405,
      "yFrom" : 26,
      "yTo" : 116
   },
   "LB120" : {
      "xFrom" : 680,
      "xTo" : 410,
      "yFrom" : 26,
      "yTo" : 176
   },
   "LB121" : {
      "xFrom" : 575,
      "xTo" : 405,
      "yFrom" : 26,
      "yTo" : 176
   },
   "LB122" : {
      "xFrom" : 755,
      "xTo" : 870,
      "yFrom" : 26,
      "yTo" : 146
   },
   "LB123" : {
      "xFrom" : 660,
      "xTo" : 465,
      "yFrom" : 26,
      "yTo" : 116
   },
   "LB124" : {
      "xFrom" : 620,
      "xTo" : 840,
      "yFrom" : 26,
      "yTo" : 146
   },
   "LB125" : {
      "xFrom" : 570,
      "xTo" : 25,
      "yFrom" : 26,
      "yTo" : 86
   },
   "LB126" : {
      "xFrom" : 670,
      "xTo" : 880,
      "yFrom" : 26,
      "yTo" : 116
   },
   "LB127" : {
      "xFrom" : 780,
      "xTo" : 550,
      "yFrom" : 26,
      "yTo" : 146
   },
   "LB128" : {
      "xFrom" : 745,
      "xTo" : 50,
      "yFrom" : 26,
      "yTo" : 86
   },
   "LB129" : {
      "xFrom" : 645,
      "xTo" : 35,
      "yFrom" : 26,
      "yTo" : 86
   },
   "LB13" : {
      "xFrom" : 125,
      "xTo" : 410,
      "yFrom" : 26,
      "yTo" : 116
   },
   "LB130" : {
      "xFrom" : 775,
      "xTo" : 60,
      "yFrom" : 26,
      "yTo" : 86
   },
   "LB131" : {
      "xFrom" : 650,
      "xTo" : 40,
      "yFrom" : 26,
      "yTo" : 86
   },
   "LB132" : {
      "xFrom" : 585,
      "xTo" : 50,
      "yFrom" : 26,
      "yTo" : 116
   },
   "LB133" : {
      "xFrom" : 635,
      "xTo" : 485,
      "yFrom" : 26,
      "yTo" : 86
   },
   "LB134" : {
      "xFrom" : 685,
      "xTo" : 855,
      "yFrom" : 26,
      "yTo" : 146
   },
   "LB135" : {
      "xFrom" : 790,
      "xTo" : 555,
      "yFrom" : 26,
      "yTo" : 146
   },
   "LB136" : {
      "xFrom" : 735,
      "xTo" : 865,
      "yFrom" : 26,
      "yTo" : 146
   },
   "LB137" : {
      "xFrom" : 800,
      "xTo" : 560,
      "yFrom" : 26,
      "yTo" : 146
   },
   "LB138" : {
      "xFrom" : 730,
      "xTo" : 860,
      "yFrom" : 26,
      "yTo" : 146
   },
   "LB139" : {
      "xFrom" : 705,
      "xTo" : 535,
      "yFrom" : 26,
      "yTo" : 146
   },
   "LB14" : {
      "xFrom" : 315,
      "xTo" : 425,
      "yFrom" : 26,
      "yTo" : 116
   },
   "LB140" : {
      "xFrom" : 655,
      "xTo" : 845,
      "yFrom" : 26,
      "yTo" : 146
   },
   "LB141" : {
      "xFrom" : 725,
      "xTo" : 20,
      "yFrom" : 26,
      "yTo" : 176
   },
   "LB142" : {
      "xFrom" : 600,
      "xTo" : 60,
      "yFrom" : 26,
      "yTo" : 116
   },
   "LB143" : {
      "xFrom" : 765,
      "xTo" : 500,
      "yFrom" : 26,
      "yTo" : 86
   },
   "LB144" : {
      "xFrom" : 795,
      "xTo" : 405,
      "yFrom" : 26,
      "yTo" : 56
   },
   "LB145" : {
      "xFrom" : 590,
      "xTo" : 55,
      "yFrom" : 26,
      "yTo" : 116
   },
   "LB146" : {
      "xFrom" : 960,
      "xTo" : 910,
      "yFrom" : 26,
      "yTo" : 116
   },
   "LB147" : {
      "xFrom" : 925,
      "xTo" : 900,
      "yFrom" : 26,
      "yTo" : 116
   },
   "LB148" : {
      "xFrom" : 900,
      "xTo" : 415,
      "yFrom" : 26,
      "yTo" : 56
   },
   "LB149" : {
      "xFrom" : 950,
      "xTo" : 75,
      "yFrom" : 26,
      "yTo" : 86
   },
   "LB15" : {
      "xFrom" : 155,
      "xTo" : 20,
      "yFrom" : 26,
      "yTo" : 146
   },
   "LB150" : {
      "xFrom" : 865,
      "xTo" : 410,
      "yFrom" : 26,
      "yTo" : 56
   },
   "LB151" : {
      "xFrom" : 930,
      "xTo" : 75,
      "yFrom" : 26,
      "yTo" : 116
   },
   "LB152" : {
      "xFrom" : 905,
      "xTo" : 70,
      "yFrom" : 26,
      "yTo" : 116
   },
   "LB153" : {
      "xFrom" : 850,
      "xTo" : 35,
      "yFrom" : 26,
      "yTo" : 176
   },
   "LB154" : {
      "xFrom" : 965,
      "xTo" : 915,
      "yFrom" : 26,
      "yTo" : 116
   },
   "LB155" : {
      "xFrom" : 915,
      "xTo" : 880,
      "yFrom" : 26,
      "yTo" : 146
   },
   "LB156" : {
      "xFrom" : 920,
      "xTo" : 590,
      "yFrom" : 26,
      "yTo" : 146
   },
   "LB157" : {
      "xFrom" : 875,
      "xTo" : 580,
      "yFrom" : 26,
      "yTo" : 146
   },
   "LB158" : {
      "xFrom" : 835,
      "xTo" : 65,
      "yFrom" : 26,
      "yTo" : 86
   },
   "LB159" : {
      "xFrom" : 840,
      "xTo" : 30,
      "yFrom" : 26,
      "yTo" : 176
   },
   "LB16" : {
      "xFrom" : 240,
      "xTo" : 430,
      "yFrom" : 26,
      "yTo" : 86
   },
   "LB160" : {
      "xFrom" : 815,
      "xTo" : 815,
      "yFrom" : 26,
      "yTo" : 56
   },
   "LB161" : {
      "xFrom" : 895,
      "xTo" : 35,
      "yFrom" : 26,
      "yTo" : 146
   },
   "LB162" : {
      "xFrom" : 940,
      "xTo" : 595,
      "yFrom" : 26,
      "yTo" : 146
   },
   "LB163" : {
      "xFrom" : 870,
      "xTo" : 575,
      "yFrom" : 26,
      "yTo" : 146
   },
   "LB164" : {
      "xFrom" : 955,
      "xTo" : 830,
      "yFrom" : 26,
      "yTo" : 176
   },
   "LB165" : {
      "xFrom" : 890,
      "xTo" : 895,
      "yFrom" : 26,
      "yTo" : 116
   },
   "LB166" : {
      "xFrom" : 810,
      "xTo" : 875,
      "yFrom" : 26,
      "yTo" : 146
   },
   "LB167" : {
      "xFrom" : 885,
      "xTo" : 585,
      "yFrom" : 26,
      "yTo" : 146
   },
   "LB168" : {
      "xFrom" : 935,
      "xTo" : 420,
      "yFrom" : 26,
      "yTo" : 56
   },
   "LB169" : {
      "xFrom" : 980,
      "xTo" : 600,
      "yFrom" : 26,
      "yTo" : 146
   },
   "LB17" : {
      "xFrom" : 250,
      "xTo" : 450,
      "yFrom" : 26,
      "yTo" : 146
   },
   "LB170" : {
      "xFrom" : 975,
      "xTo" : 840,
      "yFrom" : 26,
      "yTo" : 176
   },
   "LB171" : {
      "xFrom" : 970,
      "xTo" : 835,
      "yFrom" : 26,
      "yTo" : 176
   },
   "LB172" : {
      "xFrom" : 805,
      "xTo" : 825,
      "yFrom" : 26,
      "yTo" : 176
   },
   "LB173" : {
      "xFrom" : 830,
      "xTo" : 890,
      "yFrom" : 26,
      "yTo" : 116
   },
   "LB174" : {
      "xFrom" : 820,
      "xTo" : 565,
      "yFrom" : 26,
      "yTo" : 146
   },
   "LB175" : {
      "xFrom" : 855,
      "xTo" : 570,
      "yFrom" : 26,
      "yTo" : 146
   },
   "LB176" : {
      "xFrom" : 860,
      "xTo" : 70,
      "yFrom" : 26,
      "yTo" : 86
   },
   "LB177" : {
      "xFrom" : 825,
      "xTo" : 25,
      "yFrom" : 26,
      "yTo" : 176
   },
   "LB178" : {
      "xFrom" : 880,
      "xTo" : 40,
      "yFrom" : 26,
      "yTo" : 176
   },
   "LB179" : {
      "xFrom" : 910,
      "xTo" : 480,
      "yFrom" : 26,
      "yTo" : 116
   },
   "LB18" : {
      "xFrom" : 115,
      "xTo" : 410,
      "yFrom" : 26,
      "yTo" : 146
   },
   "LB180" : {
      "xFrom" : 945,
      "xTo" : 905,
      "yFrom" : 26,
      "yTo" : 116
   },
   "LB181" : {
      "xFrom" : 845,
      "xTo" : 475,
      "yFrom" : 26,
      "yTo" : 116
   },
   "LB182" : {
      "xFrom" : 1025,
      "xTo" : 610,
      "yFrom" : 26,
      "yTo" : 146
   },
   "LB183" : {
      "xFrom" : 1080,
      "xTo" : 620,
      "yFrom" : 26,
      "yTo" : 146
   },
   "LB184" : {
      "xFrom" : 1000,
      "xTo" : 605,
      "yFrom" : 26,
      "yTo" : 146
   },
   "LB185" : {
      "xFrom" : 1010,
      "xTo" : 920,
      "yFrom" : 26,
      "yTo" : 116
   },
   "LB186" : {
      "xFrom" : 1105,
      "xTo" : 625,
      "yFrom" : 26,
      "yTo" : 146
   },
   "LB187" : {
      "xFrom" : 1070,
      "xTo" : 615,
      "yFrom" : 26,
      "yTo" : 146
   },
   "LB188" : {
      "xFrom" : 1100,
      "xTo" : 50,
      "yFrom" : 26,
      "yTo" : 176
   },
   "LB189" : {
      "xFrom" : 990,
      "xTo" : 485,
      "yFrom" : 26,
      "yTo" : 116
   },
   "LB19" : {
      "xFrom" : 275,
      "xTo" : 465,
      "yFrom" : 26,
      "yTo" : 146
   },
   "LB190" : {
      "xFrom" : 1020,
      "xTo" : 515,
      "yFrom" : 26,
      "yTo" : 86
   },
   "LB191" : {
      "xFrom" : 1055,
      "xTo" : 45,
      "yFrom" : 26,
      "yTo" : 146
   },
   "LB192" : {
      "xFrom" : 1035,
      "xTo" : 925,
      "yFrom" : 26,
      "yTo" : 116
   },
   "LB193" : {
      "xFrom" : 985,
      "xTo" : 505,
      "yFrom" : 26,
      "yTo" : 86
   },
   "LB194" : {
      "xFrom" : 1085,
      "xTo" : 525,
      "yFrom" : 26,
      "yTo" : 86
   },
   "LB195" : {
      "xFrom" : 1065,
      "xTo" : 520,
      "yFrom" : 26,
      "yTo" : 86
   },
   "LB196" : {
      "xFrom" : 1005,
      "xTo" : 820,
      "yFrom" : 26,
      "yTo" : 56
   },
   "LB197" : {
      "xFrom" : 1095,
      "xTo" : 830,
      "yFrom" : 26,
      "yTo" : 56
   },
   "LB198" : {
      "xFrom" : 1090,
      "xTo" : 825,
      "yFrom" : 26,
      "yTo" : 56
   },
   "LB199" : {
      "xFrom" : 1015,
      "xTo" : 885,
      "yFrom" : 26,
      "yTo" : 146
   },
   "LB2" : {
      "xFrom" : 35,
      "xTo" : 405,
      "yFrom" : 26,
      "yTo" : 86
   },
   "LB20" : {
      "xFrom" : 260,
      "xTo" : 440,
      "yFrom" : 26,
      "yTo" : 86
   },
   "LB200" : {
      "xFrom" : 1050,
      "xTo" : 490,
      "yFrom" : 26,
      "yTo" : 116
   },
   "LB201" : {
      "xFrom" : 1030,
      "xTo" : 45,
      "yFrom" : 26,
      "yTo" : 176
   },
   "LB202" : {
      "xFrom" : 1110,
      "xTo" : 500,
      "yFrom" : 26,
      "yTo" : 116
   },
   "LB203" : {
      "xFrom" : 1040,
      "xTo" : 40,
      "yFrom" : 26,
      "yTo" : 146
   },
   "LB204" : {
      "xFrom" : 1060,
      "xTo" : 495,
      "yFrom" : 26,
      "yTo" : 116
   },
   "LB205" : {
      "xFrom" : 995,
      "xTo" : 510,
      "yFrom" : 26,
      "yTo" : 86
   },
   "LB207" : {
      "xFrom" : 1145,
      "xTo" : 80,
      "yFrom" : 26,
      "yTo" : 116
   },
   "LB208" : {
      "xFrom" : 1150,
      "xTo" : 535,
      "yFrom" : 26,
      "yTo" : 86
   },
   "LB21" : {
      "xFrom" : 230,
      "xTo" : 815,
      "yFrom" : 26,
      "yTo" : 176
   },
   "LB217" : {
      "xFrom" : 1190,
      "xTo" : 420,
      "yFrom" : 26,
      "yTo" : 176
   },
   "LB22" : {
      "xFrom" : 280,
      "xTo" : 470,
      "yFrom" : 26,
      "yTo" : 146
   },
   "LB220" : {
      "xFrom" : 1140,
      "xTo" : 630,
      "yFrom" : 26,
      "yTo" : 146
   },
   "LB221" : {
      "xFrom" : 1170,
      "xTo" : 835,
      "yFrom" : 26,
      "yTo" : 56
   },
   "LB222" : {
      "xFrom" : 1195,
      "xTo" : 60,
      "yFrom" : 26,
      "yTo" : 176
   },
   "LB223" : {
      "xFrom" : 1130,
      "xTo" : 845,
      "yFrom" : 26,
      "yTo" : 176
   },
   "LB226" : {
      "xFrom" : 1175,
      "xTo" : 895,
      "yFrom" : 26,
      "yTo" : 146
   },
   "LB23" : {
      "xFrom" : 295,
      "xTo" : 480,
      "yFrom" : 26,
      "yTo" : 146
   },
   "LB230" : {
      "xFrom" : 1120,
      "xTo" : 530,
      "yFrom" : 26,
      "yTo" : 86
   },
   "LB231" : {
      "xFrom" : 1200,
      "xTo" : 65,
      "yFrom" : 26,
      "yTo" : 176
   },
   "LB232" : {
      "xFrom" : 1185,
      "xTo" : 425,
      "yFrom" : 26,
      "yTo" : 56
   },
   "LB237" : {
      "xFrom" : 1160,
      "xTo" : 80,
      "yFrom" : 26,
      "yTo" : 86
   },
   "LB238" : {
      "xFrom" : 1155,
      "xTo" : 55,
      "yFrom" : 26,
      "yTo" : 176
   },
   "LB239" : {
      "xFrom" : 1125,
      "xTo" : 935,
      "yFrom" : 26,
      "yTo" : 116
   },
   "LB24" : {
      "xFrom" : 185,
      "xTo" : 830,
      "yFrom" : 26,
      "yTo" : 116
   },
   "LB240" : {
      "xFrom" : 1180,
      "xTo" : 635,
      "yFrom" : 26,
      "yTo" : 146
   },
   "LB241" : {
      "xFrom" : 1165,
      "xTo" : 415,
      "yFrom" : 26,
      "yTo" : 176
   },
   "LB243" : {
      "xFrom" : 1115,
      "xTo" : 930,
      "yFrom" : 26,
      "yTo" : 116
   },
   "LB247" : {
      "xFrom" : 1135,
      "xTo" : 890,
      "yFrom" : 26,
      "yTo" : 146
   },
   "LB25" : {
      "xFrom" : 65,
      "xTo" : 405,
      "yFrom" : 26,
      "yTo" : 146
   },
   "LB26" : {
      "xFrom" : 290,
      "xTo" : 815,
      "yFrom" : 26,
      "yTo" : 146
   },
   "LB27" : {
      "xFrom" : 215,
      "xTo" : 445,
      "yFrom" : 26,
      "yTo" : 146
   },
   "LB28" : {
      "xFrom" : 80,
      "xTo" : 815,
      "yFrom" : 26,
      "yTo" : 116
   },
   "LB29" : {
      "xFrom" : 55,
      "xTo" : 810,
      "yFrom" : 26,
      "yTo" : 116
   },
   "LB3" : {
      "xFrom" : 270,
      "xTo" : 15,
      "yFrom" : 26,
      "yTo" : 116
   },
   "LB30" : {
      "xFrom" : 60,
      "xTo" : 400,
      "yFrom" : 26,
      "yTo" : 146
   },
   "LB31" : {
      "xFrom" : 300,
      "xTo" : 820,
      "yFrom" : 26,
      "yTo" : 146
   },
   "LB32" : {
      "xFrom" : 90,
      "xTo" : 10,
      "yFrom" : 26,
      "yTo" : 116
   },
   "LB33" : {
      "xFrom" : 150,
      "xTo" : 805,
      "yFrom" : 26,
      "yTo" : 176
   },
   "LB34" : {
      "xFrom" : 305,
      "xTo" : 485,
      "yFrom" : 26,
      "yTo" : 146
   },
   "LB35" : {
      "xFrom" : 310,
      "xTo" : 420,
      "yFrom" : 26,
      "yTo" : 116
   },
   "LB36" : {
      "xFrom" : 220,
      "xTo" : 835,
      "yFrom" : 26,
      "yTo" : 116
   },
   "LB37" : {
      "xFrom" : 15,
      "xTo" : 800,
      "yFrom" : 26,
      "yTo" : 146
   },
   "LB38" : {
      "xFrom" : 105,
      "xTo" : 825,
      "yFrom" : 26,
      "yTo" : 116
   },
   "LB39" : {
      "xFrom" : 40,
      "xTo" : 10,
      "yFrom" : 26,
      "yTo" : 206
   },
   "LB4" : {
      "xFrom" : 25,
      "xTo" : 800,
      "yFrom" : 26,
      "yTo" : 116
   },
   "LB40" : {
      "xFrom" : 75,
      "xTo" : 400,
      "yFrom" : 26,
      "yTo" : 176
   },
   "LB41" : {
      "xFrom" : 195,
      "xTo" : 420,
      "yFrom" : 26,
      "yTo" : 86
   },
   "LB42" : {
      "xFrom" : 190,
      "xTo" : 435,
      "yFrom" : 26,
      "yTo" : 146
   },
   "LB43" : {
      "xFrom" : 170,
      "xTo" : 430,
      "yFrom" : 26,
      "yTo" : 146
   },
   "LB44" : {
      "xFrom" : 175,
      "xTo" : 805,
      "yFrom" : 26,
      "yTo" : 146
   },
   "LB45" : {
      "xFrom" : 160,
      "xTo" : 810,
      "yFrom" : 26,
      "yTo" : 176
   },
   "LB46" : {
      "xFrom" : 110,
      "xTo" : 15,
      "yFrom" : 26,
      "yTo" : 86
   },
   "LB47" : {
      "xFrom" : 245,
      "xTo" : 435,
      "yFrom" : 26,
      "yTo" : 86
   },
   "LB48" : {
      "xFrom" : 30,
      "xTo" : 10,
      "yFrom" : 26,
      "yTo" : 86
   },
   "LB49" : {
      "xFrom" : 165,
      "xTo" : 425,
      "yFrom" : 26,
      "yTo" : 146
   },
   "LB5" : {
      "xFrom" : 200,
      "xTo" : 25,
      "yFrom" : 26,
      "yTo" : 146
   },
   "LB50" : {
      "xFrom" : 135,
      "xTo" : 415,
      "yFrom" : 26,
      "yTo" : 146
   },
   "LB51" : {
      "xFrom" : 225,
      "xTo" : 425,
      "yFrom" : 26,
      "yTo" : 86
   },
   "LB52" : {
      "xFrom" : 120,
      "xTo" : 415,
      "yFrom" : 26,
      "yTo" : 86
   },
   "LB53" : {
      "xFrom" : 100,
      "xTo" : 410,
      "yFrom" : 26,
      "yTo" : 86
   },
   "LB54" : {
      "xFrom" : 235,
      "xTo" : 15,
      "yFrom" : 26,
      "yTo" : 206
   },
   "LB55" : {
      "xFrom" : 145,
      "xTo" : 415,
      "yFrom" : 26,
      "yTo" : 116
   },
   "LB56" : {
      "xFrom" : 45,
      "xTo" : 10,
      "yFrom" : 26,
      "yTo" : 146
   },
   "LB57" : {
      "xFrom" : 130,
      "xTo" : 15,
      "yFrom" : 26,
      "yTo" : 146
   },
   "LB58" : {
      "xFrom" : 95,
      "xTo" : 820,
      "yFrom" : 26,
      "yTo" : 116
   },
   "LB59" : {
      "xFrom" : 210,
      "xTo" : 440,
      "yFrom" : 26,
      "yTo" : 146
   },
   "LB6" : {
      "xFrom" : 70,
      "xTo" : 800,
      "yFrom" : 26,
      "yTo" : 176
   },
   "LB60" : {
      "xFrom" : 285,
      "xTo" : 475,
      "yFrom" : 26,
      "yTo" : 146
   },
   "LB61" : {
      "xFrom" : 205,
      "xTo" : 810,
      "yFrom" : 26,
      "yTo" : 146
   },
   "LB62" : {
      "xFrom" : 10,
      "xTo" : 400,
      "yFrom" : 26,
      "yTo" : 116
   },
   "LB63" : {
      "xFrom" : 470,
      "xTo" : 835,
      "yFrom" : 26,
      "yTo" : 146
   },
   "LB64" : {
      "xFrom" : 340,
      "xTo" : 435,
      "yFrom" : 26,
      "yTo" : 116
   },
   "LB65" : {
      "xFrom" : 455,
      "xTo" : 455,
      "yFrom" : 26,
      "yTo" : 116
   },
   "LB66" : {
      "xFrom" : 410,
      "xTo" : 825,
      "yFrom" : 26,
      "yTo" : 146
   },
   "LB67" : {
      "xFrom" : 420,
      "xTo" : 30,
      "yFrom" : 26,
      "yTo" : 116
   },
   "LB68" : {
      "xFrom" : 325,
      "xTo" : 20,
      "yFrom" : 26,
      "yTo" : 116
   },
   "LB69" : {
      "xFrom" : 380,
      "xTo" : 25,
      "yFrom" : 26,
      "yTo" : 116
   },
   "LB7" : {
      "xFrom" : 255,
      "xTo" : 455,
      "yFrom" : 26,
      "yTo" : 146
   },
   "LB70" : {
      "xFrom" : 360,
      "xTo" : 445,
      "yFrom" : 26,
      "yTo" : 86
   },
   "LB71" : {
      "xFrom" : 425,
      "xTo" : 10,
      "yFrom" : 26,
      "yTo" : 176
   },
   "LB72" : {
      "xFrom" : 355,
      "xTo" : 400,
      "yFrom" : 26,
      "yTo" : 56
   },
   "LB73" : {
      "xFrom" : 460,
      "xTo" : 465,
      "yFrom" : 26,
      "yTo" : 86
   },
   "LB74" : {
      "xFrom" : 495,
      "xTo" : 855,
      "yFrom" : 26,
      "yTo" : 116
   },
   "LB75" : {
      "xFrom" : 375,
      "xTo" : 460,
      "yFrom" : 26,
      "yTo" : 116
   },
   "LB76" : {
      "xFrom" : 345,
      "xTo" : 495,
      "yFrom" : 26,
      "yTo" : 146
   },
   "LB77" : {
      "xFrom" : 450,
      "xTo" : 505,
      "yFrom" : 26,
      "yTo" : 146
   },
   "LB78" : {
      "xFrom" : 335,
      "xTo" : 430,
      "yFrom" : 26,
      "yTo" : 116
   },
   "LB79" : {
      "xFrom" : 370,
      "xTo" : 840,
      "yFrom" : 26,
      "yTo" : 116
   },
   "LB8" : {
      "xFrom" : 140,
      "xTo" : 420,
      "yFrom" : 26,
      "yTo" : 146
   },
   "LB80" : {
      "xFrom" : 330,
      "xTo" : 20,
      "yFrom" : 26,
      "yTo" : 86
   },
   "LB81" : {
      "xFrom" : 320,
      "xTo" : 490,
      "yFrom" : 26,
      "yTo" : 146
   },
   "LB82" : {
      "xFrom" : 475,
      "xTo" : 510,
      "yFrom" : 26,
      "yTo" : 146
   },
   "LB83" : {
      "xFrom" : 490,
      "xTo" : 520,
      "yFrom" : 26,
      "yTo" : 146
   },
   "LB84" : {
      "xFrom" : 350,
      "xTo" : 440,
      "yFrom" : 26,
      "yTo" : 116
   },
   "LB85" : {
      "xFrom" : 405,
      "xTo" : 450,
      "yFrom" : 26,
      "yTo" : 116
   },
   "LB86" : {
      "xFrom" : 435,
      "xTo" : 455,
      "yFrom" : 26,
      "yTo" : 86
   },
   "LB87" : {
      "xFrom" : 485,
      "xTo" : 515,
      "yFrom" : 26,
      "yTo" : 146
   },
   "LB88" : {
      "xFrom" : 390,
      "xTo" : 445,
      "yFrom" : 26,
      "yTo" : 116
   },
   "LB89" : {
      "xFrom" : 440,
      "xTo" : 500,
      "yFrom" : 26,
      "yTo" : 146
   },
   "LB9" : {
      "xFrom" : 20,
      "xTo" : 400,
      "yFrom" : 26,
      "yTo" : 86
   },
   "LB90" : {
      "xFrom" : 415,
      "xTo" : 30,
      "yFrom" : 26,
      "yTo" : 206
   },
   "LB91" : {
      "xFrom" : 465,
      "xTo" : 830,
      "yFrom" : 26,
      "yTo" : 146
   },
   "LB92" : {
      "xFrom" : 500,
      "xTo" : 35,
      "yFrom" : 26,
      "yTo" : 116
   },
   "LB93" : {
      "xFrom" : 535,
      "xTo" : 40,
      "yFrom" : 26,
      "yTo" : 116
   },
   "LB94" : {
      "xFrom" : 540,
      "xTo" : 45,
      "yFrom" : 26,
      "yTo" : 116
   },
   "LB95" : {
      "xFrom" : 530,
      "xTo" : 525,
      "yFrom" : 26,
      "yTo" : 146
   },
   "LB96" : {
      "xFrom" : 525,
      "xTo" : 860,
      "yFrom" : 26,
      "yTo" : 116
   },
   "LB97" : {
      "xFrom" : 560,
      "xTo" : 865,
      "yFrom" : 26,
      "yTo" : 116
   },
   "LB98" : {
      "xFrom" : 510,
      "xTo" : 820,
      "yFrom" : 26,
      "yTo" : 176
   },
   "LB99" : {
      "xFrom" : 545,
      "xTo" : 15,
      "yFrom" : 26,
      "yTo" : 176
   },
   "LR14CA" : {
      "xFrom" : 690,
      "xTo" : 495,
      "yFrom" : 26,
      "yTo" : 86
   },
   "LR1CA" : {
      "xFrom" : 480,
      "xTo" : 470,
      "yFrom" : 26,
      "yTo" : 86
   },
   "LR2CA" : {
      "xFrom" : 365,
      "xTo" : 20,
      "yFrom" : 26,
      "yTo" : 206
   },
   "LR3CA" : {
      "xFrom" : 445,
      "xTo" : 460,
      "yFrom" : 26,
      "yTo" : 86
   },
   "LR4CA" : {
      "xFrom" : 385,
      "xTo" : 450,
      "yFrom" : 26,
      "yTo" : 86
   },
   "LR5" : {
      "xFrom" : 400,
      "xTo" : 25,
      "yFrom" : 26,
      "yTo" : 206
   },
   "LR6CA" : {
      "xFrom" : 395,
      "xTo" : 845,
      "yFrom" : 26,
      "yTo" : 116
   },
   "LR7CA" : {
      "xFrom" : 430,
      "xTo" : 850,
      "yFrom" : 26,
      "yTo" : 116
   }
}
